Pokegipsy/__init__.py
Pokegipsy/pokemon.csv
Pokegipsy/random_pokemon.py
Pokegipsy-1.1.1.dist-info/METADATA
Pokegipsy-1.1.1.dist-info/WHEEL
Pokegipsy-1.1.1.dist-info/top_level.txt
Pokegipsy-1.1.1.dist-info/RECORD
